quaspy/__init__.py
quaspy/factoring/__init__.py
quaspy/factoring/sampling.py
quaspy/factoring/general/__init__.py
quaspy/factoring/general/postprocessing/__init__.py
quaspy/factoring/general/postprocessing/ekera/__init__.py
quaspy/factoring/general/postprocessing/ekera/internal/__init__.py
quaspy/factoring/general/postprocessing/ekera/internal/collection.py
quaspy/factoring/general/postprocessing/ekera/test/__init__.py
quaspy/factoring/general/postprocessing/ekera/test/__main__.py
quaspy/factoring/general/postprocessing/shor/__init__.py
quaspy/factoring/rsa/__init__.py
quaspy/factoring/rsa/postprocessing/__init__.py
quaspy/logarithmfinding/__init__.py
quaspy/logarithmfinding/sampling.py
quaspy/logarithmfinding/general/__init__.py
quaspy/logarithmfinding/general/sampling.py
quaspy/logarithmfinding/general/postprocessing/__init__.py
quaspy/logarithmfinding/short/__init__.py
quaspy/logarithmfinding/short/sampling.py
quaspy/logarithmfinding/short/postprocessing/__init__.py
quaspy/math/__init__.py
quaspy/math/babai.py
quaspy/math/continued_fractions.py
quaspy/math/crt.py
quaspy/math/gram_schmidt.py
quaspy/math/groups.py
quaspy/math/kappa.py
quaspy/math/lagrange.py
quaspy/math/matrix_solvers.py
quaspy/math/modular.py
quaspy/math/norms.py
quaspy/math/primes.py
quaspy/math/projections.py
quaspy/math/random.py
quaspy/orderfinding/__init__.py
quaspy/orderfinding/general/__init__.py
quaspy/orderfinding/general/sampling.py
quaspy/orderfinding/general/postprocessing/__init__.py
quaspy/orderfinding/general/postprocessing/ekera/__init__.py
quaspy/orderfinding/general/postprocessing/ekera/internal/__init__.py
quaspy/orderfinding/general/postprocessing/ekera/internal/algorithms.py
quaspy/orderfinding/general/postprocessing/ekera/internal/collection.py
quaspy/orderfinding/general/postprocessing/ekera/internal/solve.py
quaspy/orderfinding/general/postprocessing/ekera/test/__init__.py
quaspy/orderfinding/general/postprocessing/ekera/test/__main__.py
quaspy/utils/__init__.py
quaspy-0.9.4.dist-info/licenses/LICENSE.md
quaspy-0.9.4.dist-info/METADATA
quaspy-0.9.4.dist-info/WHEEL
quaspy-0.9.4.dist-info/top_level.txt
quaspy-0.9.4.dist-info/RECORD
