Metadata-Version: 2.4
Name: quaspy
Version: 0.9.4
Summary: The Quaspy library for Python for simulating and post-processing various quantum algorithms, including Shor's algorithms and Ekerå–Håstad's variations of Shor's algorithms.
Author-email: Martin Ekerå <ekera@kth.se>
License-Expression: MIT
Project-URL: Homepage, https://github.com/ekera/quaspy
Project-URL: Repository, https://github.com/ekera/quaspy
Project-URL: Bug Tracker, https://github.com/ekera/quaspy/issues
Classifier: Programming Language :: Python :: 3
Classifier: Operating System :: OS Independent
Requires-Python: >=3.6
License-File: LICENSE.md
Requires-Dist: gmpy2
Requires-Dist: secret
Dynamic: license-file
